verilog/full_adder.v
module full_adder(
    input a, b, cin,
    output sum, carry
);
    assign sum   = a ^ b ^ cin;
    assign carry = (a & b) | (b & cin) | (a & cin);
endmodule

verilog/full_adder_tb.v
`timescale 1ns/1ps

module full_adder_tb;

    reg a, b, cin;
    wire sum, carry;

    full_adder dut (
        .a(a),
        .b(b),
        .cin(cin),
        .sum(sum),
        .carry(carry)
    );

    initial begin
        $dumpfile("full_adder.vcd");
        $dumpvars(0, full_adder_tb);

        $display("A B Cin | Sum Carry");
        $monitor("%b %b  %b  |  %b    %b", a, b, cin, sum, carry);

        a=0; b=0; cin=0; #10;
        a=0; b=0; cin=1; #10;
        a=0; b=1; cin=0; #10;
        a=0; b=1; cin=1; #10;
        a=1; b=0; cin=0; #10;
        a=1; b=0; cin=1; #10;
        a=1; b=1; cin=0; #10;
        a=1; b=1; cin=1; #10;

        $finish;
    end

endmodule

verilog/full_adder.vcd
$date
	Wed Jan 07 10:37:14 2026
$end
$version
	Icarus Verilog
$end
$timescale
	1ps
$end
$scope module full_adder_tb $end
$var wire 1 ! sum $end
$var wire 1 " carry $end
$var reg 1 # a $end
$var reg 1 $ b $end
$var reg 1 % cin $end
$scope module dut $end
$var wire 1 # a $end
$var wire 1 $ b $end
$var wire 1 " carry $end
$var wire 1 % cin $end
$var wire 1 ! sum $end
$upscope $end
$upscope $end
$enddefinitions $end
#0
$dumpvars
0%
0$
0#
0"
0!
$end
#10000
1!
1%
#20000
0%
1$
#30000
1"
0!
1%
#40000
0"
1!
0%
0$
1#
#50000
1"
0!
1%
#60000
0%
1$
#70000
1!
1%
